{
  "dataset_revision": "d3fb88f8f02e40887cd149695127462bbcf29b4a",
  "task_name": "BIOSSES",
  "mteb_version": "1.38.54",
  "scores": {
    "test": [
      {
        "pearson": 0.880452,
        "spearman": 0.859833,
        "cosine_pearson": 0.880452,
        "cosine_spearman": 0.859833,
        "manhattan_pearson": 0.86292,
        "manhattan_spearman": 0.855399,
        "euclidean_pearson": 0.860235,
        "euclidean_spearman": 0.851706,
        "main_score": 0.859833,
        "hf_subset": "default",
        "languages": [
          "eng-Latn"
        ]
      }
    ]
  },
  "evaluation_time": 340.8095679283142,
  "kg_co2_emissions": null
}