{
  "dataset_revision": "a0d554a64d88156834ff5ae9920b964011b16384",
  "task_name": "STS12",
  "mteb_version": "1.38.54",
  "scores": {
    "test": [
      {
        "pearson": 0.80663,
        "spearman": 0.72427,
        "cosine_pearson": 0.80663,
        "cosine_spearman": 0.72427,
        "manhattan_pearson": 0.752279,
        "manhattan_spearman": 0.714327,
        "euclidean_pearson": 0.744685,
        "euclidean_spearman": 0.707951,
        "main_score": 0.72427,
        "hf_subset": "default",
        "languages": [
          "eng-Latn"
        ]
      }
    ]
  },
  "evaluation_time": 1372.418956041336,
  "kg_co2_emissions": null
}