{
  "dataset_revision": "ae752c7c21bf194d8b67fd573edf7ae58183cbe3",
  "task_name": "STS15",
  "mteb_version": "1.38.54",
  "scores": {
    "test": [
      {
        "pearson": 0.850472,
        "spearman": 0.864351,
        "cosine_pearson": 0.850472,
        "cosine_spearman": 0.864351,
        "manhattan_pearson": 0.858958,
        "manhattan_spearman": 0.863313,
        "euclidean_pearson": 0.854792,
        "euclidean_spearman": 0.858899,
        "main_score": 0.864351,
        "hf_subset": "default",
        "languages": [
          "eng-Latn"
        ]
      }
    ]
  },
  "evaluation_time": 1340.7037739753723,
  "kg_co2_emissions": null
}